fingerGeoparser/__init__.py
fingerGeoparser/geoparser.py
fingerGeoparser/output_formatter.py
fingerGeoparser/toponym_coder.py
fingerGeoparser/toponym_tagger.py
tests/test_geoparsing.py
fingerGeoparser-0.2.0.dist-info/LICENSE
fingerGeoparser-0.2.0.dist-info/METADATA
fingerGeoparser-0.2.0.dist-info/WHEEL
fingerGeoparser-0.2.0.dist-info/top_level.txt
fingerGeoparser-0.2.0.dist-info/RECORD
