Metadata-Version: 2.1
Name: fingerGeoparser
Version: 0.2.0
Summary: A geoparser for Finnish texts
Home-page: https://github.com/Tadusko/fi-geoparser
Author: Tatu Leppämäki
Author-email: tatu.leppamaki@helsinki.fi
License: MIT License
Keywords: geoparser,NLP,GIS,Finnish
License-File: LICENSE
Requires-Dist: pandas
Requires-Dist: spacy ==3.5.2
Requires-Dist: spacy-transformers ==1.1.9
Requires-Dist: tqdm
Requires-Dist: aiohttp
